MANIFEST.in
README.rst
__init__.py
setup.py
docs/CHANGELOG.rst
docs/LICENSE.rst
docs/api.rst
docs/conf.py
docs/glossary.rst
docs/index.rst
redturtle/__init__.py
redturtle.historymanager.egg-info/PKG-INFO
redturtle.historymanager.egg-info/SOURCES.txt
redturtle.historymanager.egg-info/dependency_links.txt
redturtle.historymanager.egg-info/entry_points.txt
redturtle.historymanager.egg-info/namespace_packages.txt
redturtle.historymanager.egg-info/not-zip-safe
redturtle.historymanager.egg-info/requires.txt
redturtle.historymanager.egg-info/top_level.txt
redturtle/historymanager/README.txt
redturtle/historymanager/__init__.py
redturtle/historymanager/configure.zcml
redturtle/historymanager/adapters/__init__.py
redturtle/historymanager/adapters/configure.zcml
redturtle/historymanager/browser/__init__.py
redturtle/historymanager/browser/configure.zcml
redturtle/historymanager/browser/manager.py
redturtle/historymanager/profiles/default/metadata.xml
redturtle/historymanager/tests/__init__.py
redturtle/historymanager/tests/base.py
redturtle/historymanager/tests/test_doctest.py