Metadata-Version: 1.1
Name: redturtle.historymanager
Version: 0.9.1
Summary: RedTurtle History Manager
Home-page: http://pypi.python.org/pypi/redturtle.historymanager
Author: RedTurtleTechnology
Author-email: sviluppoplone@redturtle.it
License: BSD
Keywords: Plone,Python
Platform: UNKNOWN
Classifier: Framework :: Plone
Classifier: Programming Language :: Python
